ais_data_to_tspi/__init__.py
ais_data_to_tspi/data_to_TSPI.py
tests/__init__.py
tests/test_myfunctions.py
ais_data_to_tspi-0.0.0.dist-info/METADATA
ais_data_to_tspi-0.0.0.dist-info/WHEEL
ais_data_to_tspi-0.0.0.dist-info/top_level.txt
ais_data_to_tspi-0.0.0.dist-info/RECORD
