Metadata-Version: 2.1
Name: ais-data-to-tspi
Version: 0.0.0
Summary: Generate TSPI text files from AIS data
Home-page: UNKNOWN
Author: Josef Zapletal
License: None
Platform: UNKNOWN
Requires-Dist: pandas (==1.4.1)
